ShunjianYingdeXinrendeLengdushu/README.md
ShunjianYingdeXinrendeLengdushu/__init__.py
ShunjianYingdeXinrendeLengdushu/__main__.py
ShunjianYingdeXinrendeLengdushu/file.epub
ShunjianYingdeXinrendeLengdushu/index.html
ShunjianYingdeXinrendeLengdushu/css/__init__.py
ShunjianYingdeXinrendeLengdushu/css/annotations.css
ShunjianYingdeXinrendeLengdushu/css/main.css
ShunjianYingdeXinrendeLengdushu/css/normalize.css
ShunjianYingdeXinrendeLengdushu/css/popup.css
ShunjianYingdeXinrendeLengdushu/font/__init__.py
ShunjianYingdeXinrendeLengdushu/font/fontello.eot
ShunjianYingdeXinrendeLengdushu/font/fontello.svg
ShunjianYingdeXinrendeLengdushu/font/fontello.ttf
ShunjianYingdeXinrendeLengdushu/font/fontello.woff
ShunjianYingdeXinrendeLengdushu/img/__init__.py
ShunjianYingdeXinrendeLengdushu/img/annotator-glyph-sprite.png
ShunjianYingdeXinrendeLengdushu/img/annotator-icon-sprite.png
ShunjianYingdeXinrendeLengdushu/img/apple-touch-icon.png
ShunjianYingdeXinrendeLengdushu/img/cancelfullscreen.png
ShunjianYingdeXinrendeLengdushu/img/close.png
ShunjianYingdeXinrendeLengdushu/img/fullscreen.png
ShunjianYingdeXinrendeLengdushu/img/loader.gif
ShunjianYingdeXinrendeLengdushu/img/menu-icon.png
ShunjianYingdeXinrendeLengdushu/img/save.png
ShunjianYingdeXinrendeLengdushu/img/saved.png
ShunjianYingdeXinrendeLengdushu/img/settings-s.png
ShunjianYingdeXinrendeLengdushu/img/settings.png
ShunjianYingdeXinrendeLengdushu/img/star.png
ShunjianYingdeXinrendeLengdushu/js/__init__.py
ShunjianYingdeXinrendeLengdushu/js/epub.js
ShunjianYingdeXinrendeLengdushu/js/epub.min.js
ShunjianYingdeXinrendeLengdushu/js/epub.min.map
ShunjianYingdeXinrendeLengdushu/js/hooks.min.js
ShunjianYingdeXinrendeLengdushu/js/hooks.min.map
ShunjianYingdeXinrendeLengdushu/js/reader.js
ShunjianYingdeXinrendeLengdushu/js/reader.js.map
ShunjianYingdeXinrendeLengdushu/js/reader.min.js
ShunjianYingdeXinrendeLengdushu/js/reader.min.map
ShunjianYingdeXinrendeLengdushu/js/hooks/__init__.py
shunjian_yingde_xinrende_lengdushu-2022.10.11.0.dist-info/METADATA
shunjian_yingde_xinrende_lengdushu-2022.10.11.0.dist-info/WHEEL
shunjian_yingde_xinrende_lengdushu-2022.10.11.0.dist-info/entry_points.txt
shunjian_yingde_xinrende_lengdushu-2022.10.11.0.dist-info/top_level.txt
shunjian_yingde_xinrende_lengdushu-2022.10.11.0.dist-info/RECORD
